CHANGES.txt
README.txt
setup.cfg
setup.py
src/collective/__init__.py
src/collective.gsa64.egg-info/PKG-INFO
src/collective.gsa64.egg-info/SOURCES.txt
src/collective.gsa64.egg-info/dependency_links.txt
src/collective.gsa64.egg-info/entry_points.txt
src/collective.gsa64.egg-info/namespace_packages.txt
src/collective.gsa64.egg-info/not-zip-safe
src/collective.gsa64.egg-info/requires.txt
src/collective.gsa64.egg-info/top_level.txt
src/collective/gsa64/__init__.py
src/collective/gsa64/configure.zcml
src/collective/gsa64/controlpanel.py
src/collective/gsa64/events.py
src/collective/gsa64/feed.pt
src/collective/gsa64/interfaces.py
src/collective/gsa64/multipart.py
src/collective/gsa64/setuphandlers.py
src/collective/gsa64/browser/__init__.py
src/collective/gsa64/browser/robots.py
src/collective/gsa64/browser/search.pt
src/collective/gsa64/browser/search.py
src/collective/gsa64/browser/transform.xslt
src/collective/gsa64/browser/trivial.xml
src/collective/gsa64/profiles/default/browserlayer.xml
src/collective/gsa64/profiles/default/controlpanel.xml
src/collective/gsa64/profiles/default/import_steps.xml
src/collective/gsa64/profiles/default/metadata.xml
src/collective/gsa64/profiles/default/registry.xml