Metadata-Version: 1.0
Name: collective.gsa64
Version: 1.0-beta4
Summary: Feeds protocol implementation and search integration
Home-page: UNKNOWN
Author: Malthe Borch and Mustapha Benali
Author-email: mborch@gmail.com
License: GPL
Keywords: plone gsa google search feeds
Platform: UNKNOWN
Classifier: Framework :: Plone
Classifier: Framework :: Zope2
Classifier: Programming Language :: Python
